[
    {
        "id": 1,
        "title": "M293 | Kochrezept | Kochburg",
        "category": "Web Development",
        "description": "A simple one page Website for a recipe. It was built using HTML and CSS.",
        "link": "https://r06nv4ldr.github.io/M293_Kochburg/",
        "technologies": [
            "HTML",
            "CSS"
        ],
        "images": [
            {
                "src": "assets/img/projects/Kochburg.png",
                "alt": "Kochburg Website"
            },
            {
                "src": "assets/img/projects/Kochburg.png",
                "alt": "Kochburg Website"
            }
        ]
    },
    {
        "id": 2,
        "title": "M293 | Mediensammlung",
        "category": "Web Development",
        "description": "A simple one page Website for a movie collection. It was built using HTML and CSS.",
        "link": "https://r06nv4ldr.github.io/M293_Mediensammlung/",
        "technologies": [
            "HTML",
            "CSS"
        ],
        "images": [
            {
                "src": "assets/img/projects/Mediensammlung.png",
                "alt": "Mediensammlung Website"
            }
        ]
    },
    {
        "id": 3,
        "title": "A 2 bonZai",
        "category": "Web Development",
        "description": "Website made as a project for ICT BBC. It was built using HTML and CSS",
        "link": "https://r06nv4ldr.github.io/a2bonzai/",
        "technologies": [
            "HTML",
            "CSS"
        ],
        "images": [
            {
                "src": "assets/img/projects/A2BonZai_fullscreen.png",
                "alt": "A2BonZai_Website"
            }
        ]
    },
    {
        "id": 4,
        "title": "M293 Portfolio",
        "category": "Web Development",
        "description": "This is a detailed description of this website you're on right now. It was built using HTML, CSS, and JavaScript.",
        "link": "https://r06nv4ldr.github.io/M293_Portfolio/",
        "technologies": [
            "HTML",
            "CSS",
            "JavaScript"
        ],
        "images": [
            {
                "src": "assets/img/logos/RB_5_transparent2.png",
                "alt": "Portfolio Website"
            }
        ]
    },
    {
        "id": 5,
        "title": "Finance App",
        "category": "Web Application",
        "description": "Finance App is an application that allows users to add budgets for various kinds of expenses. It features user authentication and real-time data updates.",
        "link": "https://github.com/R06NV4LDR",
        "technologies": [
            "Node.js",
            "Express",
            "MongoDB"
        ],
        "images": [
            {
                "src": "assets/img/projects/financeapp_dashboard.png",
                "alt": "Finance App"
            },
            {
                "src": "assets/img/projects/financeapp_dashboard_detail.png",
                "alt": "Finance App"
            },
            {
                "src": "assets/img/projects/financeapp_expenses_detail.png",
                "alt": "Finance App"
            }
        ]
    },
    {
        "id": 6,
        "title": "Product Rater",
        "category": "Mobile Application",
        "description": "Product Rater is an application that allows users to rate different products. It features user authentication and real-time data updates.",
        "link": "https://github.com/R06NV4LDR",
        "technologies": [
            "React-Native",
            "Expo",
            "Firestore"
        ],
        "images": [
            {
                "src": "assets/img/projects/ProductRater_HomeScreen.png",
                "alt": "Product Rater Home Screen"
            },
            {
                "src": "assets/img/projects/ProductRater_Categories.png",
                "alt": "Product Rater Categories"
            },
            {
                "src": "assets/img/projects/ProductRater_Category.png",
                "alt": "Product Rater Category"
            },
            {
                "src": "assets/img/projects/ProductRater_ProductDetail.png",
                "alt": "Product Rater Product Detail"
            },
            {
                "src": "assets/img/projects/ProductRater_Scan.png",
                "alt": "Product Rater Scanner"
            }
        ]
    },
    {
        "id": 7,
        "title": "Project 3",
        "category": "Web Development",
        "description": "Description of Project 3.",
        "link": "https://github.com/R06NV4LDR",
        "technologies": [
            "React",
            "Redux",
            "Firebase"
        ],
        "images": [
            {
                "src": "assets/img/logos/RB_5_transparent2.png",
                "alt": "RB_5_transparent2"
            }
        ]
    },
    {
        "id": 8,
        "title": "Project 4",
        "category": "Web Development",
        "description": "Description of Project 4.",
        "link": "https://github.com/R06NV4LDR",
        "technologies": [
            "Vue",
            "Vuex",
            "Axios"
        ],
        "images": [
            {
                "src": "assets/img/logos/RB_5_transparent2.png",
                "alt": "RB_5_transparent2"
            }
        ]
    },
    {
        "id": 9,
        "title": "Project 1",
        "category": "Web Development",
        "description": "This is a detailed description of Project 1. It was built using HTML, CSS, and JavaScript.",
        "link": "https://github.com/R06NV4LDR",
        "technologies": [
            "HTML",
            "CSS",
            "JavaScript"
        ],
        "images": [
            {
                "src": "assets/img/logos/RB_5_transparent2.png",
                "alt": "RB_5_transparent2"
            }
        ]
    },
    {
        "id": 10,
        "title": "Product Rater",
        "category": "Web Development",
        "description": "Product Rater is an application that allows users to rate different products. It features user authentication and real-time data updates.",
        "link": "https://github.com/R06NV4LDR",
        "technologies": [
            "Node.js",
            "Express",
            "MongoDB"
        ],
        "images": [
            {
                "src": "assets/img/logos/RB_5_transparent2.png",
                "alt": "RB_5_transparent2"
            }
        ]
    },
    {
        "id": 11,
        "title": "Project 3",
        "category": "Web Development",
        "description": "Description of Project 3.",
        "link": "https://github.com/R06NV4LDR",
        "technologies": [
            "React",
            "Redux",
            "Firebase"
        ],
        "images": [
            {
                "src": "assets/img/logos/RB_5_transparent2.png",
                "alt": "RB_5_transparent2"
            }
        ]
    },
    {
        "id": 12,
        "title": "Project 4",
        "category": "Web Development",
        "description": "Description of Project 4.",
        "link": "https://github.com/R06NV4LDR",
        "technologies": [
            "Vue",
            "Vuex",
            "Axios"
        ],
        "images": [
            {
                "src": "assets/img/logos/RB_5_transparent2.png",
                "alt": "RB_5_transparent2"
            }
        ]
    },
    {
        "id": 13,
        "title": "Product Rater",
        "category": "Web Development",
        "description": "Product Rater is an application that allows users to rate different products. It features user authentication and real-time data updates.",
        "link": "https://github.com/R06NV4LDR",
        "technologies": [
            "Node.js",
            "Express",
            "MongoDB"
        ],
        "images": [
            {
                "src": "assets/img/logos/RB_5_transparent2.png",
                "alt": "RB_5_transparent2"
            }
        ]
    },
    {
        "id": 14,
        "title": "Project 3",
        "category": "Web Development",
        "description": "Description of Project 3.",
        "link": "https://github.com/R06NV4LDR",
        "technologies": [
            "React",
            "Redux",
            "Firebase"
        ],
        "images": [
            {
                "src": "assets/img/logos/RB_5_transparent2.png",
                "alt": "RB_5_transparent2"
            }
        ]
    },
    {
        "id": 15,
        "title": "Project 4",
        "category": "Web Development",
        "description": "Description of Project 4.",
        "link": "https://github.com/R06NV4LDR",
        "technologies": [
            "Vue",
            "Vuex",
            "Axios"
        ],
        "images": [
            {
                "src": "assets/img/logos/RB_5_transparent2.png",
                "alt": "RB_5_transparent2"
            }
        ]
    },
    {
        "id": 16,
        "title": "Product Rater",
        "category": "Web Development",
        "description": "Product Rater is an application that allows users to rate different products. It features user authentication and real-time data updates.",
        "link": "https://github.com/R06NV4LDR",
        "technologies": [
            "Node.js",
            "Express",
            "MongoDB"
        ],
        "images": [
            {
                "src": "assets/img/logos/RB_5_transparent2.png",
                "alt": "RB_5_transparent2"
            }
        ]
    },
    {
        "id": 17,
        "title": "Project 3",
        "category": "Web Development",
        "description": "Description of Project 3.",
        "link": "https://github.com/R06NV4LDR",
        "technologies": [
            "React",
            "Redux",
            "Firebase"
        ],
        "images": [
            {
                "src": "assets/img/logos/RB_5_transparent2.png",
                "alt": "RB_5_transparent2"
            }
        ]
    },
    {
        "id": 18,
        "title": "Project 4",
        "category": "Web Development",
        "description": "Description of Project 4.",
        "link": "https://github.com/R06NV4LDR",
        "technologies": [
            "Vue",
            "Vuex",
            "Axios"
        ],
        "images": [
            {
                "src": "assets/img/logos/RB_5_transparent2.png",
                "alt": "RB_5_transparent2"
            }
        ]
    },
    {
        "id": 19,
        "title": "Product Rater",
        "category": "Web Development",
        "description": "Product Rater is an application that allows users to rate different products. It features user authentication and real-time data updates.",
        "link": "https://github.com/R06NV4LDR",
        "technologies": [
            "Node.js",
            "Express",
            "MongoDB"
        ],
        "images": [
            {
                "src": "assets/img/logos/RB_5_transparent2.png",
                "altText": "RB_5_transparent2"
            }
        ]
    },
    {
        "id": 20,
        "title": "Project 3",
        "category": "Web Development",
        "description": "Description of Project 3.",
        "link": "https://github.com/R06NV4LDR",
        "technologies": [
            "React",
            "Redux",
            "Firebase"
        ],
        "images": [
            {
                "src": "assets/img/logos/RB_5_transparent2.png",
                "altText": "RB_5_transparent2"
            }
        ]
    },
    {
        "id": 15,
        "title": "Project 4",
        "category": "Web Development",
        "description": "Description of Project 4.",
        "link": "https://github.com/R06NV4LDR",
        "technologies": [
            "Vue",
            "Vuex",
            "Axios"
        ],
        "images": [
            {
                "src": "assets/img/logos/RB_5_transparent2.png",
                "altText": "RB_5_transparent2"
            }
        ]
    }
]